latex2pdfa/__init__.py
latex2pdfa/binaries/ghostscript/Licence
latex2pdfa/binaries/ghostscript/gs-923-linux-x86_64
latex2pdfa/latex2pdfa.py
latex2pdfa/resources/PDFA_def.ps
latex2pdfa/resources/lib_PDFA_def.ps
latex2pdfa/resources/pdfa.config
latex2pdfa/resources/sRGB.icc
latex2pdfa/resources/sample.xmpdata
latex2pdfa/utils.py
latex2pdfa-1.0.5.dist-info/entry_points.txt
latex2pdfa-1.0.5.dist-info/LICENSE
latex2pdfa-1.0.5.dist-info/WHEEL
latex2pdfa-1.0.5.dist-info/METADATA
latex2pdfa-1.0.5.dist-info/RECORD
