Metadata-Version: 2.1
Name: latex2pdfa
Version: 1.0.5
Summary: A command line utility to automate the process of compiling a LaTex project to a PDF complaint with the PDF/A standard
License: GPLv3
Author: Abdeladim S.
Requires-Python: >=3.10,<4.0
Classifier: License :: Other/Proprietary License
Classifier: Programming Language :: Python :: 3
Classifier: Programming Language :: Python :: 3.10
Classifier: Programming Language :: Python :: 3.11
Requires-Dist: rich (==12.4.4)
